{
    "raw_data_info": {
        "raw_data_name": "3cb896e6-7086-4ee8-8f69-68fe3aee6f3e",
        "date": "2024-10-18",
        "publisher": "2차 저작",
        "publication_year": "2022-08-01",
        "school": "초등학교",
        "grade": "3학년",
        "semester": "2학기",
        "subject": "수학",
        "revision_year": "2015"
    },
    "source_data_info": {
        "source_data_name": "S3_초등_3_008594",
        "2009_achievement_standard": [
            " "
        ],
        "2015_achievement_standard": [
            "[4수01-08] 나누는 수가 한 자리 수인 나눗셈의 계산 원리를 이해하고 그 계산을 할 수 있으며, 나눗셈에서 몫과 나머지의 의미를 안다."
        ],
        "2022_achievement_standard": [
            "[4수01-06] 나누는 수가 한 자리 수인 나눗셈의 계산 원리를 이해하고 그 계산을 할 수 있으며, 나눗셈에서 몫과 나머지의 의미를 안다."
        ],
        "level_of_difficulty": "하",
        "types_of_problems": "객관식"
    },
    "learning_data_info": [
        {
            "class_num": 2,
            "class_name": "문항(텍스트)",
            "class_info_list": [
                {
                    "Type": "Bounding_Box",
                    "Type_value": [
                        [
                            68.19,
                            8.38,
                            556.74,
                            35.05
                        ]
                    ],
                    "text_description": "나머지가 더 큰 것을 찾아 선택해 보세요."
                },
                {
                    "Type": "Bounding_Box",
                    "Type_value": [
                        [
                            328.76,
                            69.42,
                            625.3,
                            99.59
                        ]
                    ],
                    "text_description": "㉠ $515 \\div 4$ ㉡ $516 \\div 5$"
                }
            ]
        },
        {
            "class_num": 1,
            "class_name": "정답(텍스트)",
            "class_info_list": [
                {
                    "Type": "Bounding_Box",
                    "Type_value": [
                        [
                            53.28,
                            140.97,
                            79.57,
                            167.36
                        ]
                    ],
                    "text_description": "㉠"
                }
            ]
        },
        {
            "class_num": 1,
            "class_name": "해설(텍스트)",
            "class_info_list": [
                {
                    "Type": "Bounding_Box",
                    "Type_value": [
                        [
                            26.07,
                            223.05,
                            562.2,
                            289.66
                        ]
                    ],
                    "text_description": "㉡ $516 \\div 5=103 \\cdots 1$ 따라서 $3>1$ 이므로 나머지가 더 큰 것은 ㉠입니다."
                }
            ]
        },
        {
            "class_num": 1,
            "class_name": "해설(이미지)",
            "class_info_list": [
                {
                    "Type": "Bounding_Box",
                    "Type_value": [
                        [
                            83.28,
                            187.01,
                            265.2,
                            215.4
                        ]
                    ],
                    "text_description": "$515 \\div 4=128 \\cdots 3$"
                }
            ]
        }
    ]
}