{
    "raw_data_info": {
        "raw_data_name": "ca240499-140d-4087-93cc-8fd2ba68c280",
        "date": "2024-10-18",
        "publisher": "2차 저작",
        "publication_year": "2022-08-01",
        "school": "초등학교",
        "grade": "4학년",
        "semester": "1학기",
        "subject": "수학",
        "revision_year": "2015"
    },
    "source_data_info": {
        "source_data_name": "S3_초등_4_008289",
        "2009_achievement_standard": [
            " "
        ],
        "2015_achievement_standard": [
            "[4수02-04] 구체물이나 평면도형의 밀기, 뒤집기, 돌리기 활동을 통하여 그 변화를 이해한다."
        ],
        "2022_achievement_standard": [
            "[4수03-04] 구체물이나 평면도형의 밀기, 뒤집기, 돌리기 활동을 통하여 그 변화를 이해한다."
        ],
        "level_of_difficulty": "하",
        "types_of_problems": "객관식"
    },
    "learning_data_info": [
        {
            "class_num": 2,
            "class_name": "문항(텍스트)",
            "class_info_list": [
                {
                    "Type": "Bounding_Box",
                    "Type_value": [
                        [
                            63.2,
                            3.94,
                            892.8,
                            33.54
                        ]
                    ],
                    "text_description": "서랍장을 왼 쪽으로 밀었을 때의 그림을 보고 알맞은 말을 선택하세요."
                },
                {
                    "Type": "Bounding_Box",
                    "Type_value": [
                        [
                            72,
                            286,
                            894.4,
                            315.6
                        ]
                    ],
                    "text_description": "서랍장의 모양은 변하지 않고 위치는 (바뀝니다, 바뀌지 않습니다)."
                }
            ]
        },
        {
            "class_num": 1,
            "class_name": "문항(이미지)",
            "class_info_list": [
                {
                    "Type": "Bounding_Box",
                    "Type_value": [
                        [
                            103.2,
                            41.34,
                            868.8,
                            282.34
                        ]
                    ],
                    "text_description": "서랍장을 왼쪽으로 밀어야지. 서랍장을 왼쪽으로 미는 그림입니다. 왼쪽으로 밀면 이렇게 돼. 왼쪽으로 민 그림입니다."
                }
            ]
        },
        {
            "class_num": 1,
            "class_name": "정답(텍스트)",
            "class_info_list": [
                {
                    "Type": "Bounding_Box",
                    "Type_value": [
                        [
                            61.8,
                            334.8,
                            162.4,
                            362.6
                        ]
                    ],
                    "text_description": "바뀝니다."
                }
            ]
        },
        {
            "class_num": 1,
            "class_name": "해설(텍스트)",
            "class_info_list": [
                {
                    "Type": "Bounding_Box",
                    "Type_value": [
                        [
                            60.8,
                            381.2,
                            832,
                            409.2
                        ]
                    ],
                    "text_description": "서랍장을 왼쪽으로 밀면 서랍장의 모양은 변하지 않고 위치는 바뀝니다."
                }
            ]
        }
    ]
}