{
    "raw_data_info": {
        "raw_data_name": "224e7378-e3af-4264-9020-2d98ab773cd6",
        "date": "2024-08-27",
        "publisher": "교학사",
        "publication_year": "2015-01-01",
        "school": "초등학교",
        "grade": "5학년",
        "semester": "1학기",
        "subject": "수학",
        "revision_year": "2015"
    },
    "source_data_info": {
        "source_data_name": "S3_초등_5_004546",
        "2009_achievement_standard": [
            " "
        ],
        "2015_achievement_standard": [
            "[6수01-08] 분모가 다른 분수의 덧셈과 뺄셈의 계산 원리를 이해하고 그 계산을 할 수 있다."
        ],
        "2022_achievement_standard": [
            "[6수01-08] 분모가 다른 분수의 덧셈과 뺄셈의 계산 원리를 탐구하고 그 계산을 할 수 있다."
        ],
        "level_of_difficulty": "하",
        "types_of_problems": "주관식"
    },
    "learning_data_info": [
        {
            "class_num": 1,
            "class_name": "문항(텍스트)",
            "class_info_list": [
                {
                    "Type": "Bounding_Box",
                    "Type_value": [
                        [
                            34.78,
                            5.74,
                            102.78,
                            40.74
                        ]
                    ],
                    "text_description": "$\\frac{5}{12}-\\frac{3}{10}$"
                }
            ]
        },
        {
            "class_num": 1,
            "class_name": "정답(이미지)",
            "class_info_list": [
                {
                    "Type": "Bounding_Box",
                    "Type_value": [
                        [
                            -1.22,
                            85.27,
                            39.78,
                            129.27
                        ]
                    ],
                    "text_description": "$1 \\frac{11}{42}$"
                }
            ]
        },
        {
            "class_num": 1,
            "class_name": "해설(이미지)",
            "class_info_list": [
                {
                    "Type": "Bounding_Box",
                    "Type_value": [
                        [
                            29.78,
                            41.27,
                            314.78,
                            89.27
                        ]
                    ],
                    "text_description": "$\\frac{23}{6}-\\frac{18}{7}=\\frac{161}{42}-\\frac{108}{42}=\\frac{53}{42}=1 \\frac{11}{42}$"
                }
            ]
        }
    ]
}