{
    "raw_data_info": {
        "raw_data_name": "ff7e6ef8-0275-48ef-9734-396e3e082ea3",
        "date": "2024-10-02",
        "publisher": "대교",
        "publication_year": "2022-08-01",
        "school": "초등학교",
        "grade": "6학년",
        "semester": "2학기",
        "subject": "수학",
        "revision_year": "2015"
    },
    "source_data_info": {
        "source_data_name": "S3_초등_6_003041",
        "2009_achievement_standard": [
            " "
        ],
        "2015_achievement_standard": [
            "[6수01-11] 분수의 나눗셈의 계산 원리를 이해하고 그 계산을 할 수 있다."
        ],
        "2022_achievement_standard": [
            "[6수01-11] 분수의 나눗셈의 계산 원리를 탐구하고 그 계산을 할 수 있다."
        ],
        "level_of_difficulty": "중",
        "types_of_problems": "주관식"
    },
    "learning_data_info": [
        {
            "class_num": 1,
            "class_name": "문항(텍스트)",
            "class_info_list": [
                {
                    "Type": "Bounding_Box",
                    "Type_value": [
                        [
                            5,
                            6.91,
                            393,
                            110.91
                        ]
                    ],
                    "text_description": "상자 한 개를 포장하는 데 리본 $\\frac{9}{10} \\mathrm{~m}$가 필요합니다. 리본 27m로 똑같은 상자 몇 개를 포장할 수 있는지 구해 보세요. 도수리"
                }
            ]
        },
        {
            "class_num": 1,
            "class_name": "문항(이미지)",
            "class_info_list": [
                {
                    "Type": "Bounding_Box",
                    "Type_value": [
                        [
                            11,
                            136.91,
                            303,
                            292.91
                        ]
                    ],
                    "text_description": "리본이 매어져 있는 선물박스 상자"
                }
            ]
        },
        {
            "class_num": 1,
            "class_name": "정답(텍스트)",
            "class_info_list": [
                {
                    "Type": "Bounding_Box",
                    "Type_value": [
                        [
                            80,
                            349.5,
                            177,
                            379.5
                        ]
                    ],
                    "text_description": "30 개"
                }
            ]
        },
        {
            "class_num": 1,
            "class_name": "해설(이미지)",
            "class_info_list": [
                {
                    "Type": "Bounding_Box",
                    "Type_value": [
                        [
                            38.8,
                            289.18,
                            301.2,
                            332.06
                        ]
                    ],
                    "text_description": "$27 \\div \\frac{9}{10}=(27 \\div 9) \\times 10=30$ (개)"
                }
            ]
        }
    ]
}