{
    "raw_data_info": {
        "raw_data_name": "3c57f271-efe6-4598-9c29-9fa10f1a0ce7",
        "date": "2024-08-27",
        "publisher": "교학사",
        "publication_year": "2015-01-01",
        "school": "초등학교",
        "grade": "6학년",
        "semester": "2학기",
        "subject": "수학",
        "revision_year": "2015"
    },
    "source_data_info": {
        "source_data_name": "S3_초등_6_005473",
        "2009_achievement_standard": [
            " "
        ],
        "2015_achievement_standard": [
            "[6수02-08] 원기둥을 알고, 구성 요소, 성질, 전개도를 이해한다."
        ],
        "2022_achievement_standard": [
            "[6수03-07] 원기둥, 원뿔, 구를 이해하고, 구성 요소와 성질을 탐구하고 설명할 수 있다.",
            "[6수03-08] 원기둥의 전개도를 그릴 수 있다."
        ],
        "level_of_difficulty": "중",
        "types_of_problems": "주관식"
    },
    "learning_data_info": [
        {
            "class_num": 1,
            "class_name": "문항(텍스트)",
            "class_info_list": [
                {
                    "Type": "Bounding_Box",
                    "Type_value": [
                        [
                            16.43,
                            18.29,
                            452.55,
                            79.89
                        ]
                    ],
                    "text_description": "다음 전개도를 접어서 만들어지는 원기둥의 높이를 나타내는 선분을 모두 찾아 써 보세요."
                }
            ]
        },
        {
            "class_num": 1,
            "class_name": "문항(이미지)",
            "class_info_list": [
                {
                    "Type": "Bounding_Box",
                    "Type_value": [
                        [
                            137.39,
                            97.55,
                            328.75,
                            253.27
                        ]
                    ],
                    "text_description": "원기둥의 전개도가 있다. 가운데 직사각형을 기준으로 위아래로 원 2개가 붙어 있다. 직사각형의 꼭짓점에 ㄱ, ㄴ, ㄷ, ㄹ로 표시되어 있다."
                }
            ]
        },
        {
            "class_num": 1,
            "class_name": "정답(텍스트)",
            "class_info_list": [
                {
                    "Type": "Bounding_Box",
                    "Type_value": [
                        [
                            175.15,
                            267.99,
                            354.99,
                            296.15
                        ]
                    ],
                    "text_description": "선분 ㄱㄴ, 선분 ㄹㄷ"
                }
            ]
        },
        {
            "class_num": 1,
            "class_name": "해설(텍스트)",
            "class_info_list": [
                {
                    "Type": "Bounding_Box",
                    "Type_value": [
                        [
                            33.07,
                            303.99,
                            314.67,
                            326.71
                        ]
                    ],
                    "text_description": "원기둥의 높이는 옆면의 세로와 같습니다."
                }
            ]
        }
    ]
}