{
    "raw_data_info": {
        "raw_data_name": "f71b051c-0758-4d58-a9e0-99286e557902",
        "date": "2024-08-27",
        "publisher": "교학사",
        "publication_year": "2015-01-01",
        "school": "초등학교",
        "grade": "5학년",
        "semester": "2학기",
        "subject": "수학",
        "revision_year": "2015"
    },
    "source_data_info": {
        "source_data_name": "S3_초등_5_004888",
        "2009_achievement_standard": [
            " "
        ],
        "2015_achievement_standard": [
            "[6수02-05] 직육면체와 정육면체의 겨냥도와 전개도를 그릴 수 있다."
        ],
        "2022_achievement_standard": [
            "[6수03-04] 직육면체와 정육면체의 겨냥도와 전개도를 그릴 수 있다."
        ],
        "level_of_difficulty": "중",
        "types_of_problems": "주관식"
    },
    "learning_data_info": [
        {
            "class_num": 1,
            "class_name": "문항(텍스트)",
            "class_info_list": [
                {
                    "Type": "Bounding_Box",
                    "Type_value": [
                        [
                            17.97,
                            15.32,
                            474.2,
                            84.87
                        ]
                    ],
                    "text_description": "직육면체에서 색칠한 면과 수직인 모서리의 길이의 합을 구해 보세요."
                }
            ]
        },
        {
            "class_num": 1,
            "class_name": "문항(이미지)",
            "class_info_list": [
                {
                    "Type": "Bounding_Box",
                    "Type_value": [
                        [
                            130.51,
                            91.53,
                            354.94,
                            238.33
                        ]
                    ],
                    "text_description": "가로 30cm, 세로9cm, 높이12cm로 구성되어있는 직육면체의 겨냥도이다."
                }
            ]
        },
        {
            "class_num": 1,
            "class_name": "정답(텍스트)",
            "class_info_list": [
                {
                    "Type": "Bounding_Box",
                    "Type_value": [
                        [
                            319.36,
                            261.71,
                            395.54,
                            288.21
                        ]
                    ],
                    "text_description": "120cm"
                }
            ]
        },
        {
            "class_num": 1,
            "class_name": "해설(텍스트)",
            "class_info_list": [
                {
                    "Type": "Bounding_Box",
                    "Type_value": [
                        [
                            39.5,
                            302.29,
                            472.54,
                            353.62
                        ]
                    ],
                    "text_description": "색칠한 면과 수직인 모서리는 길이가 30cm 인 모서리로 모두 4 개가 있으므로 $30 \\times 4=120(\\mathrm{~cm})$ 입니다."
                }
            ]
        }
    ]
}