{
    "raw_data_info": {
        "raw_data_name": "6d86ed9c-a4a5-48dc-96ac-7fc8781c64b2",
        "date": "2024-10-18",
        "publisher": "2차 저작",
        "publication_year": "2022-08-01",
        "school": "초등학교",
        "grade": "5학년",
        "semester": "2학기",
        "subject": "수학",
        "revision_year": "2015"
    },
    "source_data_info": {
        "source_data_name": "S3_초등_5_009941",
        "2009_achievement_standard": [
            " "
        ],
        "2015_achievement_standard": [
            "[6수02-05] 직육면체와 정육면체의 겨냥도와 전개도를 그릴 수 있다."
        ],
        "2022_achievement_standard": [
            "[6수03-04] 직육면체와 정육면체의 겨냥도와 전개도를 그릴 수 있다."
        ],
        "level_of_difficulty": "하",
        "types_of_problems": "객관식"
    },
    "learning_data_info": [
        {
            "class_num": 1,
            "class_name": "문항(텍스트)",
            "class_info_list": [
                {
                    "Type": "Bounding_Box",
                    "Type_value": [
                        [
                            10.27,
                            6.73,
                            634.27,
                            60.73
                        ]
                    ],
                    "text_description": "그림과 같이 꼭짓점 ㄷ과 만나는 면들에 삼각자를 대어 보았을때 어떤 특징이 있는지 알아보고 알맞은 말을 선택하세요."
                }
            ]
        },
        {
            "class_num": 1,
            "class_name": "문항(이미지)",
            "class_info_list": [
                {
                    "Type": "Bounding_Box",
                    "Type_value": [
                        [
                            258.27,
                            61.27,
                            397.27,
                            158.27
                        ]
                    ],
                    "text_description": "각 꼭짓점 ㄱ에서 ㅇ까지의 직육면체 겨냥도이다. 꼭짓점 ㄷ과 만나는 면들에 삼각자가 붙어져있다."
                }
            ]
        },
        {
            "class_num": 1,
            "class_name": "정답(텍스트)",
            "class_info_list": [
                {
                    "Type": "Bounding_Box",
                    "Type_value": [
                        [
                            9.27,
                            188.27,
                            77.27,
                            223.27
                        ]
                    ],
                    "text_description": "(정답) 수직"
                }
            ]
        },
        {
            "class_num": 2,
            "class_name": "해설(텍스트)",
            "class_info_list": [
                {
                    "Type": "Bounding_Box",
                    "Type_value": [
                        [
                            122.27,
                            159.27,
                            534.27,
                            188.27
                        ]
                    ],
                    "text_description": "꼭짓점 ㄷ을 중심으로 모두 (평행, 수직)입니다."
                },
                {
                    "Type": "Bounding_Box",
                    "Type_value": [
                        [
                            11.27,
                            225.27,
                            152.27,
                            309.27
                        ]
                    ],
                    "text_description": "(해설)각 꼭짓점 ㄱ에서 ㅇ까지의 직육면체 겨냥도이다. 꼭짓점 ㄷ과 만나는 면들에 삼각자가 붙어져있다."
                }
            ]
        }
    ]
}