{
    "raw_data_info": {
        "raw_data_name": "b89aee0b-0ccd-4aea-b026-2df0f8c6c1da",
        "date": "2024-08-27",
        "publisher": "교학사",
        "publication_year": "2015-01-01",
        "school": "초등학교",
        "grade": "5학년",
        "semester": "1학기",
        "subject": "수학",
        "revision_year": "2015"
    },
    "source_data_info": {
        "source_data_name": "S3_초등_5_004500",
        "2009_achievement_standard": [
            " "
        ],
        "2015_achievement_standard": [
            "[6수04-01] 한 양이 변할 때 다른 양이 그에 종속하여 변하는 대응 관계를 나타낸 표에서 규칙을 찾아 설명하고, □, △ 등을 사용하여 식으로 나타낼 수 있다."
        ],
        "2022_achievement_standard": [
            "[6수02-01] 한 양이 변할 때 다른 양이 그에 종속하여 변하는 대응 관계를 나타낸 표에서 규칙을 찾아 설명하고, □, △ 등을 사용하여 식으로 나타낼 수 있다."
        ],
        "level_of_difficulty": "중",
        "types_of_problems": "주관식"
    },
    "learning_data_info": [
        {
            "class_num": 2,
            "class_name": "문항(텍스트)",
            "class_info_list": [
                {
                    "Type": "Bounding_Box",
                    "Type_value": [
                        [
                            44.33,
                            7.43,
                            427.69,
                            88.07
                        ]
                    ],
                    "text_description": "오각형 1개를 만드는 데 성냥개비가 5개 필요합니다. 오각형의 수와 성냥개비의 수 사이에는 어떤 대응 관계가 있는지 물음에 답하세요."
                },
                {
                    "Type": "Bounding_Box",
                    "Type_value": [
                        [
                            53.29,
                            194.65,
                            436.65,
                            247.77
                        ]
                    ],
                    "text_description": "오각형의 수를 ■, 성냥개비의 수를 $\\triangle$라 할 때, ■와 $\\triangle$ 사이의 대응 관계를 식으로 나타내어 보세요."
                }
            ]
        },
        {
            "class_num": 1,
            "class_name": "문항(이미지)",
            "class_info_list": [
                {
                    "Type": "Bounding_Box",
                    "Type_value": [
                        [
                            47.53,
                            94.17,
                            421.29,
                            185.05
                        ]
                    ],
                    "text_description": "성냥개비 5개를 사용해 만든 오각형이 4개가 정렬돼 있다."
                }
            ]
        },
        {
            "class_num": 1,
            "class_name": "정답(이미지)",
            "class_info_list": [
                {
                    "Type": "Bounding_Box",
                    "Type_value": [
                        [
                            159.53,
                            265.69,
                            364.97,
                            290.01
                        ]
                    ],
                    "text_description": "■ $\\times 5= \\triangle ($ 또는 $\\triangle \\div 5=$ ■ $)$"
                }
            ]
        },
        {
            "class_num": 1,
            "class_name": "해설(텍스트)",
            "class_info_list": [
                {
                    "Type": "Bounding_Box",
                    "Type_value": [
                        [
                            71.85,
                            304.09,
                            436.01,
                            341.85
                        ]
                    ],
                    "text_description": "오각형의 수에 5를 곱하면 성냥개비의 수가 됩니다. 또는 성냥개비의 수를 5로 나누면 오각형의 수가 됩니다."
                }
            ]
        }
    ]
}